.editorconfig
.gitignore
.gitlab-ci.yml
README.rst
publish.settings.sh
publish.sh
pyproject.toml
tsconfig.json
.idea/modules.xml
.idea/peek-plugin-gis-diagram.iml
.idea/inspectionProfiles/Project_Default.xml
.idea/inspectionProfiles/profiles_settings.xml
peek_plugin_gis_diagram/__init__.py
peek_plugin_gis_diagram/plugin_package.json
peek_plugin_gis_diagram.egg-info/PKG-INFO
peek_plugin_gis_diagram.egg-info/SOURCES.txt
peek_plugin_gis_diagram.egg-info/dependency_links.txt
peek_plugin_gis_diagram.egg-info/requires.txt
peek_plugin_gis_diagram.egg-info/top_level.txt
peek_plugin_gis_diagram/_private/PluginNames.py
peek_plugin_gis_diagram/_private/__init__.py
peek_plugin_gis_diagram/_private/alembic.ini
peek_plugin_gis_diagram/_private/admin-app/gisDiagram.module.ts
peek_plugin_gis_diagram/_private/admin-app/components/edit-setting-table/edit.component.html
peek_plugin_gis_diagram/_private/admin-app/components/edit-setting-table/edit.component.ts
peek_plugin_gis_diagram/_private/admin-app/components/gis-diagram-page/gis-diagram-admin-page.component.html
peek_plugin_gis_diagram/_private/admin-app/components/gis-diagram-page/gis-diagram-admin-page.component.scss
peek_plugin_gis_diagram/_private/admin-app/components/gis-diagram-page/gis-diagram-admin-page.component.ts
peek_plugin_gis_diagram/_private/alembic/__init__.py
peek_plugin_gis_diagram/_private/alembic/env.py
peek_plugin_gis_diagram/_private/alembic/script.py.mako
peek_plugin_gis_diagram/_private/alembic/versions/0b12f40fadba_added_stringint_table.py
peek_plugin_gis_diagram/_private/alembic/versions/450e040742f8_added_setting_table.py
peek_plugin_gis_diagram/_private/alembic/versions/__init__.py
peek_plugin_gis_diagram/_private/both-app/gisDiagram.component.ts
peek_plugin_gis_diagram/_private/both-app/gisDiagram.component.web.html
peek_plugin_gis_diagram/_private/both-app/gisDiagram.module.ts
peek_plugin_gis_diagram/_private/both-app/show-diagram/show-diagram.component.ts
peek_plugin_gis_diagram/_private/both-app/show-diagram/show-diagram.component.web.html
peek_plugin_gis_diagram/_private/both-assets/icon.png
peek_plugin_gis_diagram/_private/client/ClientEntryHook.py
peek_plugin_gis_diagram/_private/client/DeviceTupleDataObservableProxy.py
