Metadata-Version: 2.4
Name: peek-plugin-gis-diagram
Version: 5.0.4
Summary: Peek Plugin GisDiagram - geographic digram of Peek
Author-email: Synerty <contact@synerty.com>
Project-URL: Homepage, https://github.com/Synerty/peek-plugin-gis-diagram
Keywords: Peek,Python,Platform,synerty
Requires-Dist: peek-plugin-base==5.0.4
